PToolkit/PToolkit.py
PToolkit/PToolkit_test.py
PToolkit/Test.py
PToolkit/__init__.py
PToolkit/cmd.py
PToolkit/LabControl/LabControl.py
PToolkit/LabControl/VideoPlayer.py
PToolkit/LabControl/__init__.py
PToolkit/LabControl/assets/__init__.py
PToolkit/LabControl/assets/downarrow.png
PToolkit/LabControl/assets/downleftarrow.png
PToolkit/LabControl/assets/downrightarrow.png
PToolkit/LabControl/assets/greenled.png
PToolkit/LabControl/assets/homebutton.png
PToolkit/LabControl/assets/leftarrow.png
PToolkit/LabControl/assets/redled.png
PToolkit/LabControl/assets/rightarrow.png
PToolkit/LabControl/assets/toparrow.png
PToolkit/LabControl/assets/topleftarrow.png
PToolkit/LabControl/assets/toprightarrow.png
PToolkit/LabControl/exampleproject/Main.py
PToolkit/LabControl/exampleproject/interfaces/Arduino.py
PToolkit/LabControl/exampleproject/interfaces/LabControl.py
PToolkit/LabControl/exampleproject/interfaces/TTi_1604.py
PToolkit/LabControl/exampleproject/interfaces/blankinterface.py
PToolkit/LabControl/exampleproject/scripts/blank.py
PToolkit/LabControl/exampleproject/scripts/myfirstscript.py
PToolkit/LabControl/newproject/Main.py
PToolkit/LabControl/newproject/interfaces/blankinterface.py
PToolkit/LabControl/newproject/scripts/blank.py
PToolkit/Tools/__init__.py
PToolkit/Tools/tools.py
PToolkit/uCOM/uCOM_python.py
PToolkit-2.0.6.dist-info/LICENSE
PToolkit-2.0.6.dist-info/METADATA
PToolkit-2.0.6.dist-info/WHEEL
PToolkit-2.0.6.dist-info/entry_points.txt
PToolkit-2.0.6.dist-info/top_level.txt
PToolkit-2.0.6.dist-info/RECORD
