Metadata-Version: 2.1
Name: PToolkit
Version: 2.0.6
Summary: A set of tools to make working in a lab easier.
Home-page: https://github.com/JDVHA/PToolkit
Download-URL: https://github.com/JDVHA/PToolkit/archive/refs/tags/2.0.tar.gz
Author: H.A.J de Vries
Author-email: 
License: MIT
License-File: LICENSE
Requires-Dist: numpy
Requires-Dist: matplotlib
Requires-Dist: sympy
Requires-Dist: scipy
Requires-Dist: pyserial
